campy/__init__.py
campy/campy.py
campy/start.py
example/__init__.py
example/start.py
campy_package-0.1.0.dist-info/LICENSE.txt
campy_package-0.1.0.dist-info/METADATA
campy_package-0.1.0.dist-info/WHEEL
campy_package-0.1.0.dist-info/top_level.txt
campy_package-0.1.0.dist-info/RECORD
